Metadata-Version: 2.4
Name: signalrcore
Version: 0.9.7
Summary: A Python SignalR Core client(json and messagepack),with invocation auth and two way streaming.Compatible with azure / serverless functions.Also with automatic reconnect and manually reconnect.
Home-page: https://github.com/mandrewcito/signalrcore
Author: mandrewcito
Author-email: signalrcore@mandrewcito.dev
Keywords: signalr core client 3.1
Classifier: Programming Language :: Python :: 3.8
Classifier: License :: OSI Approved :: MIT License
Classifier: Operating System :: OS Independent
License-File: LICENSE
Requires-Dist: msgpack==1.0.2
Provides-Extra: dev
Requires-Dist: requests; extra == "dev"
Requires-Dist: flake8; extra == "dev"
Requires-Dist: coverage; extra == "dev"
Requires-Dist: pytest; extra == "dev"
Requires-Dist: pytest-cov; extra == "dev"
Dynamic: author
Dynamic: author-email
Dynamic: classifier
Dynamic: description
Dynamic: description-content-type
Dynamic: home-page
Dynamic: keywords
Dynamic: license-file
Dynamic: provides-extra
Dynamic: requires-dist
Dynamic: summary
